emcwrap/__init__.py
emcwrap/dists.py
emcwrap/experimental.py
emcwrap/moves.py
emcwrap/plots.py
emcwrap/sampler.py
emcwrap/stats.py
emcwrap/test_all.py
emcwrap/tools.py
emcwrap/test_storage/median.npy
emcwrap-0.2.5.dist-info/LICENSE
emcwrap-0.2.5.dist-info/METADATA
emcwrap-0.2.5.dist-info/WHEEL
emcwrap-0.2.5.dist-info/top_level.txt
emcwrap-0.2.5.dist-info/RECORD
