Metadata-Version: 2.1
Name: emcwrap
Version: 0.2.5
Summary: Tools for Bayesian inference using Ensemble MCMC
Home-page: https://github.com/gboehl/emcwrap
Author: Gregor Boehl
Author-email: admin@gregorboehl.com
License: MIT
Classifier: License :: OSI Approved :: MIT License
Classifier: Programming Language :: Python :: 3
Classifier: Programming Language :: Python :: 3.9
License-File: LICENSE
Requires-Dist: dime-sampler
Requires-Dist: numpy
Requires-Dist: scipy
Requires-Dist: tqdm
Requires-Dist: emcee
Requires-Dist: pandas
Requires-Dist: matplotlib
